bsblan/__init__.py
bsblan/bsblan.py
bsblan/constants.py
bsblan/exceptions.py
bsblan/models.py
bsblan/py.typed
bsblan/utility.py
python_bsblan-4.1.0.dist-info/METADATA
python_bsblan-4.1.0.dist-info/WHEEL
python_bsblan-4.1.0.dist-info/licenses/LICENSE.md
python_bsblan-4.1.0.dist-info/RECORD
