Metadata-Version: 2.4
Name: python-bsblan
Version: 4.1.0
Summary: Asynchronous Python client for BSBLAN API
Project-URL: Homepage, https://github.com/liudger/python-bsblan
Project-URL: Repository, https://github.com/liudger/python-bsblan
Project-URL: Documentation, https://github.com/liudger/python-bsblan
Project-URL: Bug Tracker, https://github.com/liudger/python-bsblan/issues
Project-URL: Changelog, https://github.com/liudger/python-bsblan/releases
Author-email: Willem-Jan van Rootselaar <liudgervr@gmail.com>
Maintainer-email: Willem-Jan van Rootselaar <liudgervr@gmail.com>
License: MIT
License-File: LICENSE.md
Keywords: api,async,bsblan,client,thermostat
Classifier: Development Status :: 3 - Alpha
Classifier: Framework :: AsyncIO
Classifier: Intended Audience :: Developers
Classifier: License :: OSI Approved :: MIT License
Classifier: Natural Language :: English
Classifier: Programming Language :: Python :: 3
Classifier: Programming Language :: Python :: 3.12
Classifier: Programming Language :: Python :: 3.13
Classifier: Programming Language :: Python :: 3.14
Classifier: Topic :: Software Development :: Libraries :: Python Modules
Requires-Python: >=3.12
Requires-Dist: aiohttp>=3.8.1
Requires-Dist: backoff>=2.2.1
Requires-Dist: mashumaro>=3.13.1
Requires-Dist: orjson>=3.9.10
Requires-Dist: packaging>=21.3
Requires-Dist: yarl>=1.7.2
